{
  "Post": {
    "title": {
      "loremWords": { "minLength": 5, "maxLength": 20 }
    },
    "views": {
      "int": {
        "min": 1,
        "max": 500
      }
    },
    "publishedDate": {
      "dateTime": {
        "min": "2018-01-01T00:00:00Z",
        "max": "2020-12-31T23:59:59Z"
      }
    },
    "authorName": {
      "string": {}
    },
    "excerpt": {
      "loremSentences": { "minLength": 2, "maxLength": 5 }
    },
    "content": {
      "loremParagraphs": { "minLength": 50, "maxLength": 200 }
    },
    "photo": {
      "regexp": "https://picsum\\.photos/seed/[0-9]{5}/1920/1080"
    }
  }
}